{
    "img":[
        {"img":"http://pic.netbian.com/uploads/allimg/200405/171302-15860779827765.jpg"},
        {"img":"http://www.4kbizhi.com/d/file/2019/12/17/small211452MJ3lU1576588492.jpg"},
        {"img":"http://www.4kbizhi.com/d/file/2020/03/21/small002245uq0kK1584721365.jpg"},
        {"img":"http://pic.netbian.com/uploads/allimg/200618/005100-1592412660d6f4.jpg"},
        {"img":"http://pic.netbian.com/uploads/allimg/190824/212516-15666531161ade.jpg"}
    ],
    "token":{"token":"123456"},
    "zhang":[
        {
        "zhang":"wkw"
        },
        {
            "zhang":"haha"
        }
    ],
    "limit":[
        {
            "img":"第一条",
            "name":"图片"
        },
        {
            "img":"第二条",
            "name":"图片"
        },
        {
            "img":"第三条",
            "name":"图片"
        },
        {
            "img":"第四条",
            "name":"图片"
        }
    ]
}